random_number.py
random_python_package_within_monorepo-0.0.1.dist-info/LICENSE.txt
random_python_package_within_monorepo-0.0.1.dist-info/METADATA
random_python_package_within_monorepo-0.0.1.dist-info/WHEEL
random_python_package_within_monorepo-0.0.1.dist-info/top_level.txt
random_python_package_within_monorepo-0.0.1.dist-info/RECORD
