Metadata-Version: 2.1
Name: random-python-package-within-monorepo
Version: 0.0.1
Summary: This will generate random number for you!
Home-page: https://github.com/davidoh0905/urban-octo-waffle
Author: David Oh
Author-email: davidoh0905@gmail.com
License: : OSI Approved :: MIT License
License-File: LICENSE.txt
